functions.py
greet.py
atomic_loop_pkg_test/__init__.py
atomic_loop_pkg_test/functions.py
atomic_loop_pkg_test/greet.py
atomic_loop_pkg_test-0.2.dist-info/License.txt
atomic_loop_pkg_test-0.2.dist-info/METADATA
atomic_loop_pkg_test-0.2.dist-info/WHEEL
atomic_loop_pkg_test-0.2.dist-info/top_level.txt
atomic_loop_pkg_test-0.2.dist-info/RECORD
