Metadata-Version: 2.1
Name: atomic-loop-pkg-test
Version: 0.2
Summary: this package provides the math functions
Home-page: https://github.com/LEO2822/python-package
Author: Mangesh
Author-email: mtkashid7@gmail.com
License: UNKNOWN
Platform: UNKNOWN
Classifier: Programming Language :: Python :: 3
Classifier: Programming Language :: Python :: 3.6
Classifier: Programming Language :: Python :: 3.7
Classifier: License :: OSI Approved :: GNU General Public License v2 or later (GPLv2+)
Classifier: Operating System :: OS Independent
